[
    {
        "code": "MDVL 0063",
        "title": "Antisemitism: A History (JUDS 0063)",
        "semesters": [
            "Fall"
        ],
        "crn": "18906"
    },
    {
        "code": "MDVL 0300M",
        "title": "Medieval Gender (ENGL 0300M)",
        "semesters": [
            "Fall"
        ],
        "crn": "19158"
    },
    {
        "code": "MDVL 0360",
        "title": "Medieval Bodies: Medieval Perspectives",
        "semesters": [
            "Spring"
        ],
        "crn": "25885"
    },
    {
        "code": "MDVL 0750N",
        "title": "Muslims, Christians, and Jews in Medieval Spain (HISP 0750N)",
        "semesters": [
            "Fall"
        ],
        "crn": "19154"
    },
    {
        "code": "MDVL 1120G",
        "title": "The Idea of Self (CLAS 1120G)",
        "semesters": [
            "Fall"
        ],
        "crn": "19121"
    },
    {
        "code": "MDVL 1205",
        "title": "The Long Fall of the Roman Empire (HIST 1205)",
        "semesters": [
            "Fall"
        ],
        "crn": "19078"
    },
    {
        "code": "MDVL 1210E",
        "title": "History of Romance Languages (HISP 1210E/FREN 1020B)",
        "semesters": [
            "Fall"
        ],
        "crn": "19153"
    },
    {
        "code": "MDVL 1630",
        "title": "The Talmud (JUDS 1630)",
        "semesters": [
            "Fall"
        ],
        "crn": "18907"
    },
    {
        "code": "MDVL 1963Q",
        "title": "Sex, Power, and God: A Medieval Perspective (HIST 1963Q)",
        "semesters": [
            "Fall"
        ],
        "crn": "19122"
    }
]